dask_felleskomponenter/__init__.py
dask_felleskomponenter/felleskomponenter/__init__.py
dask_felleskomponenter/felleskomponenter/schema.py
dask_felleskomponenter/felleskomponenter/sync_df_to_pgdb.py
dask_felleskomponenter/governance/__init__.py
dask_felleskomponenter/governance/main.py
dask_felleskomponenter/governance/checks/__init__.py
dask_felleskomponenter/governance/checks/column.py
dask_felleskomponenter/governance/checks/common.py
dask_felleskomponenter/governance/checks/geometri_encoding_kodeliste.py
dask_felleskomponenter/governance/checks/sikkerhetsnivaa_kodeliste.py
dask_felleskomponenter/governance/checks/table.py
dask_felleskomponenter/governance/checks/tilgangsnivaa_kodeliste.py
dask_felleskomponenter/tests/__init__.py
dask_felleskomponenter/tests/test_table_validation.py
dask_felleskomponenter/types/__init__.py
dask_felleskomponenter/udfs/__init__.py
dask_felleskomponenter/udfs/udf_conversions.py
dask_felleskomponenter/udfs/udf_tools.py
dask_felleskomponenter/udfs/tests/hoydekurver_registration_and_sql_tests.py
dask_felleskomponenter/udfs/tests/test_contours_udf.py
dask_felleskomponenter/udfs/tests/test_wkb_udfs.py
dask_felleskomponenter/udfs/tests/wkb_registration_and_sql_tests.py
dask_felleskomponenter-0.1.12.dist-info/licenses/LICENSE
dask_felleskomponenter-0.1.12.dist-info/METADATA
dask_felleskomponenter-0.1.12.dist-info/WHEEL
dask_felleskomponenter-0.1.12.dist-info/top_level.txt
dask_felleskomponenter-0.1.12.dist-info/RECORD
