Metadata-Version: 2.4
Name: dask-felleskomponenter
Version: 0.1.12
Summary: Felleskomponenter på DASK
Author-email: "Dataplattform@Statens Kartverk" <dataplattform@kartverket.no>
Project-URL: Homepage, https://github.com/kartverket/dask-felleskomponenter
Project-URL: Issues, https://github.com/kartverket/dask-felleskomponenter/issues
Classifier: Programming Language :: Python :: 3
Classifier: License :: OSI Approved :: MIT License
Classifier: Operating System :: OS Independent
Requires-Python: <3.14,>=3.10
License-File: LICENSE
Requires-Dist: requests
Requires-Dist: databricks-connect
Requires-Dist: pyspark==3.5.8
Requires-Dist: psycopg==3.3.2
Dynamic: license-file
